reflectionist/__init__.py
reflectionist/__main__.py
reflectionist/cli.py
reflectionist/config.py
reflectionist/database.py
reflectionist/service.py
reflectionist-0.1.2.dist-info/entry_points.txt
reflectionist-0.1.2.dist-info/WHEEL
reflectionist-0.1.2.dist-info/METADATA
reflectionist-0.1.2.dist-info/RECORD
