Metadata-Version: 2.1
Name: reflectionist
Version: 0.1.2
Summary: A simple CLI app that helps you to track your reflections during your day.
Author: Dênis Araújo da Silva
Author-email: silvadenisaraujo@gmail.com
Requires-Python: >=3.8,<4.0
Classifier: Programming Language :: Python :: 3
Classifier: Programming Language :: Python :: 3.10
Classifier: Programming Language :: Python :: 3.8
Classifier: Programming Language :: Python :: 3.9
Requires-Dist: click (>=8.0.3,<9.0.0)
Requires-Dist: typer (>=0.4.0,<0.5.0)
